sentiment_amazon_analyzer/__init__.py
sentiment_amazon_analyzer/data_importer.py
sentiment_amazon_analyzer/import_data.py
sentiment_amazon_analyzer/pickle_service.py
sentiment_amazon_analyzer/pickler.py
sentiment_amazon_analyzer/sentiment_analysis_service.py
sentiment_amazon_analyzer/sentiment_pipeline.py
sentiment_amazon_analyzer/text_normalizer.py
sentiment_amazon_analyzer/text_normalizer_service.py
sentiment_amazon_analyzer/vote_classifier.py
sentiment_amazon_analyzer/words_tokenizer.py
sentiment_amazon_analyzer/words_tokenizer_service.py
sentiment_amazon_analyzer-1.0.7.dist-info/METADATA
sentiment_amazon_analyzer-1.0.7.dist-info/WHEEL
sentiment_amazon_analyzer-1.0.7.dist-info/top_level.txt
sentiment_amazon_analyzer-1.0.7.dist-info/RECORD
