Metadata-Version: 2.1
Name: sentiment-amazon-analyzer
Version: 1.0.7
Summary: Sentiment Amazon Analyzer package
Home-page: UNKNOWN
Author: Pavle Aligrudic
Author-email: <pavleal@email.com>
License: UNKNOWN
Keywords: sentiment,amazon,analysis
Platform: UNKNOWN
Classifier: Development Status :: 3 - Alpha
Classifier: Intended Audience :: Education
Classifier: Programming Language :: Python :: 2
Classifier: Programming Language :: Python :: 3
Classifier: Operating System :: MacOS :: MacOS X
Classifier: Operating System :: Microsoft :: Windows
Requires-Dist: pandas
Requires-Dist: nltk
Requires-Dist: numpy
